bgcArgoDMQC/__init__.py
bgcArgoDMQC/configure.py
bgcArgoDMQC/diagnostic.py
bgcArgoDMQC/lut.py
bgcArgoDMQC/unit.py
bgcArgoDMQC/core/__init__.py
bgcArgoDMQC/core/core.py
bgcArgoDMQC/core/oxygen.py
bgcArgoDMQC/core/sprof.py
bgcArgoDMQC/interp/__init__.py
bgcArgoDMQC/interp/interp.py
bgcArgoDMQC/io/__init__.py
bgcArgoDMQC/io/index.py
bgcArgoDMQC/io/io.py
bgcArgoDMQC/io/load.py
bgcArgoDMQC/io/netcdf.py
bgcArgoDMQC/plot/__init__.py
bgcArgoDMQC/plot/plot.py
bgcArgoDMQC/plot/style.py
bgcArgoDMQC/util/__init__.py
bgcArgoDMQC/util/array.py
bgcArgoDMQC/util/geo.py
bgcArgoDMQC/util/stats.py
bgcArgoDMQC/util/util.py
bgcArgoDMQC-0.2.13.data/data/T_lL_tau_LUT/T_lL_tau_3830_4330.dat
bgcArgoDMQC-0.2.13.data/data/global_argo_index/ar_index_global_meta.txt.gz
bgcArgoDMQC-0.2.13.data/data/global_argo_index/ar_index_global_prof.txt.gz
bgcArgoDMQC-0.2.13.data/data/global_argo_index/argo_bio-profile_index.txt.gz
bgcArgoDMQC-0.2.13.data/data/global_argo_index/argo_synthetic-profile_index.txt.gz
bgcArgoDMQC-0.2.13.dist-info/LICENSE.txt
bgcArgoDMQC-0.2.13.dist-info/METADATA
bgcArgoDMQC-0.2.13.dist-info/WHEEL
bgcArgoDMQC-0.2.13.dist-info/top_level.txt
bgcArgoDMQC-0.2.13.dist-info/RECORD
