Metadata-Version: 2.1
Name: bgcArgoDMQC
Version: 0.2.13
Summary: A python library for quality control of BGC-Argo data
Home-page: https://github.com/ArgoCanada/bgcArgoDMQC
Author: Christopher Gordon
Author-email: chris.gordon@dfo-mpo.gc.ca
Maintainer: cgrdn
License: The MIT License (MIT)
Platform: UNKNOWN
Classifier: Programming Language :: Python :: 3.4
Classifier: Programming Language :: Python :: 3.5
Classifier: Programming Language :: Python :: 3.6
Classifier: Programming Language :: Python :: 3.7
Classifier: Programming Language :: Python :: 3.8
Classifier: Programming Language :: Python :: 3.9
Classifier: Topic :: Scientific/Engineering
Classifier: Intended Audience :: Science/Research
Classifier: Operating System :: OS Independent
Classifier: Development Status :: 3 - Alpha
Requires-Python: >=3.4
License-File: LICENSE.txt
Requires-Dist: numpy
Requires-Dist: scipy
Requires-Dist: matplotlib
Requires-Dist: gsw
Requires-Dist: netCDF4
Requires-Dist: pandas
Requires-Dist: seaborn
Requires-Dist: cmocean
